{
  "$schema": "https://raw.githubusercontent.com/streetsidesoftware/cspell/main/cspell.schema.json",
  "version": "0.2",
  "language": "en",
  "words": [
    "antlr",
    "centralises",
    "cnext",
    "codegen",
    "consolas",
    "cspell",
    "ctype",
    "debounce",
    "debounced",
    "dedup",
    "depcruise",
    "esbenp",
    "fclose",
    "fgetc",
    "fgets",
    "fopen",
    "fputc",
    "fputs",
    "getenv",
    "graphviz",
    "jlaustill",
    "jscpd",
    "knip",
    "laustill",
    "memchr",
    "millis",
    "myheader",
    "notexist",
    "ossm",
    "objc",
    "oxlint",
    "pullup",
    "renameable",
    "setjmp",
    "sonarqube",
    "stdarg",
    "stdbool",
    "stddef",
    "stdint",
    "strchr",
    "strrchr",
    "strstr",
    "transpile",
    "transpiled",
    "transpiler",
    "tsmorph",
    "usec",
    "webview"
  ],
  "ignorePaths": [
    "node_modules",
    "dist",
    "out",
    "coverage",
    "*.vsix",
    "package-lock.json",
    ".vscode-test",
    "syntaxes/**",
    "snippets/**",
    "src/__tests__/fixtures/**",
    "src/__tests__/integration/fixtures/**"
  ],
  "enableFiletypes": ["typescript", "markdown", "json"],
  "dictionaries": ["typescript", "node", "npm", "softwareTerms"]
}
